roundhouse/__init__.py
roundhouse/cli.py
roundhouse/serializer.py
roundhouse/utils.py
roundhouse/contrib/__init__.py
roundhouse/contrib/serializers/__init__.py
roundhouse/contrib/serializers/bson.py
roundhouse/contrib/serializers/json.py
roundhouse/contrib/serializers/msgpack.py
roundhouse/contrib/serializers/pickle.py
roundhouse/contrib/serializers/toml.py
roundhouse/contrib/serializers/xml.py
roundhouse/contrib/serializers/yaml.py
roundhouse-0.2.1.dist-info/DESCRIPTION.rst
roundhouse-0.2.1.dist-info/METADATA
roundhouse-0.2.1.dist-info/RECORD
roundhouse-0.2.1.dist-info/WHEEL
roundhouse-0.2.1.dist-info/entry_points.txt
roundhouse-0.2.1.dist-info/metadata.json
roundhouse-0.2.1.dist-info/top_level.txt
