Metadata-Version: 2.0
Name: roundhouse
Version: 0.2.1
Summary: Convert many serialization formats to many formats
Home-page: https://github.com/nick-allen/python-roundhouse
Author: Nick Allen
Author-email: nick.allen.cse@gmail.com
License: MIT license
Keywords: roundhouse
Platform: UNKNOWN
Classifier: Development Status :: 2 - Pre-Alpha
Classifier: License :: OSI Approved :: MIT License
Classifier: Programming Language :: Python :: 2
Classifier: Programming Language :: Python :: 2.7
Classifier: Programming Language :: Python :: 3
Classifier: Programming Language :: Python :: 3.3
Classifier: Programming Language :: Python :: 3.4
Classifier: Programming Language :: Python :: 3.5
Classifier: Programming Language :: Python :: 3.6
Requires-Dist: click (>=6,<7)
Requires-Dist: pluggy (>=0.4,<0.5)
Provides-Extra: all
Requires-Dist: bson; extra == 'all'
Requires-Dist: msgpack-python; extra == 'all'
Requires-Dist: pyyaml; extra == 'all'
Requires-Dist: toml; extra == 'all'
Requires-Dist: xmltodict; extra == 'all'
Provides-Extra: bson
Requires-Dist: bson; extra == 'bson'
Provides-Extra: msgpack
Requires-Dist: msgpack-python; extra == 'msgpack'
Provides-Extra: toml
Requires-Dist: toml; extra == 'toml'
Provides-Extra: xml
Requires-Dist: xmltodict; extra == 'xml'
Provides-Extra: yaml
Requires-Dist: pyyaml; extra == 'yaml'
